{"mumbai": 80, "policing": 78, "officers": 67, "forces": 60, "states": 54, "agencies": 49, "bombay": 49, "uniformed": 48, "countries": 45, "preventive": 45, "patrol": 45, "services": 44, "republic": 44, "members": 42, "appointed": 41, "duties": 41, "officials": 41, "courts": 39, "george": 39, "patrols": 39, "detectives": 39, "institute": 39, "unsourced": 39, "headed": 39, "enforce": 37, "carried": 37, "kingdom": 37, "guarding": 37, "constable": 37, "watchmen": 37, "constables": 37, "arrested": 37, "detective": 37, "statements": 37, "articles": 37, "powers": 34, "developed": 34, "volunteers": 34, "existed": 34, "mounted": 34, "organized": 34, "formed": 34, "france": 34, "robert": 34, "sharing": 34, "bureau": 34, "borivali": 34, "goswami": 34, "cities": 32, "enforcing": 32, "dealing": 32, "divided": 32, "prevention": 32, "greater": 32, "functions": 32, "weapons": 32, "firearms": 32, "europe": 32, "google": 32, "suburban": 32, "railway": 32, "pradesh": 32, "andheri": 32, "dayword": 32, "funded": 28, "crimes": 28, "trained": 28, "preventing": 28, "assisted": 28, "required": 28, "medieval": 28, "municipal": 28, "brought": 28, "england": 28, "policemen": 28, "london": 28, "thames": 28, "studies": 28, "founded": 28, "remained": 28, "commons": 28, "channels": 28, "persons": 24, "defined": 24, "varying": 24, "protective": 24, "ireland": 24, "higher": 24, "handling": 24, "judicial": 24, "dedicated": 24, "judges": 24, "norman": 24, "conquest": 24, "tithing": 24, "charles": 24, "registered": 24, "glasgow": 24, "marked": 24, "colquhoun": 24, "criminals": 24, "jeremy": 24, "warrant": 24, "colony": 24, "australia": 24, "portuguese": 24, "provincial": 24, "larger": 24, "varies": 24, "unmarked": 24, "qualified": 24, "examples": 24, "situations": 24, "specially": 24, "suspects": 24, "wilson": 24, "controlled": 24, "stations": 24, "samuel": 24, "oxford": 24, "inspector": 24, "bandra": 24, "shivaji": 24, "istthe": 24, "summoned": 24, "redirects": 19, "associated": 19, "authorized": 19, "referred": 19, "decades": 19, "auxiliary": 19, "prefects": 19, "carrying": 19, "tasked": 19, "protecting": 19, "patrolling": 19, "empire": 19, "acting": 19, "serving": 19, "assigned": 19, "occurred": 19, "passed": 19, "hiring": 19, "marshal": 19, "marshalcy": 19, "resulting": 19, "tithings": 19, "groups": 19, "overseen": 19, "governed": 19, "elected": 19, "organised": 19, "lieutenant": 19, "nicolas": 19, "districts": 19, "prohibited": 19, "regarded": 19, "influenced": 19, "peelian": 19, "arrests": 19, "dominion": 19, "provides": 19, "selected": 19, "foucault": 19, "produced": 19, "argued": 19, "searching": 19, "narcotics": 19, "aspects": 19, "disposal": 19, "equipped": 19, "interpol": 19, "practices": 19, "showed": 19, "highest": 19, "miranda": 19, "authorize": 19, "programs": 19, "random": 19, "unabridged": 19, "perseus": 19, "timothy": 19, "containing": 19, "richard": 19, "sheena": 19, "presidency": 19, "pertaining": 19, "starting": 19, "hemant": 19, "gafoor": 19, "jogeshwari": 19, "summons": 19, "alleged": 19, "marathi": 19, "syllable": 19, "empowered": 12, "sovereign": 12, "charged": 12, "activities": 12, "degrees": 12, "persian": 12, "scotland": 12, "derived": 12, "kingdoms": 12, "helped": 12, "citizens": 12, "delegated": 12, "places": 12, "catching": 12, "meetings": 12, "families": 12, "protected": 12, "thieves": 12, "capturing": 12, "vigiles": 12, "handled": 12, "systems": 12, "israel": 12, "mentioned": 12, "temple": 12, "talmud": 12, "mentions": 12, "salaries": 12, "regions": 12, "societies": 12, "written": 12, "nobility": 12, "enforced": 12, "households": 12, "inspectors": 12, "provinces": 12, "santas": 12, "pilgrims": 12, "intended": 12, "recorded": 12, "hermandad": 12, "extended": 12, "castilian": 12, "summary": 12, "warnings": 12, "issuing": 12, "bodies": 12, "historians": 12, "raising": 12, "captured": 12, "paying": 12, "hundreds": 12, "escaped": 12, "sheriff": 12, "nighttime": 12, "earliest": 12, "statute": 12, "winchester": 12, "regulating": 12, "monarch": 12, "institutes": 12, "largest": 12, "gabriel": 12, "prefecture": 12, "decree": 12, "fielding": 12, "organizing": 12, "salaried": 12, "borrowed": 12, "marine": 12, "scottish": 12, "followed": 12, "patrick": 12, "considered": 12, "commerce": 12, "maintained": 12, "detecting": 12, "issued": 12, "quoted": 12, "governing": 12, "whilst": 12, "nacional": 12, "janeiro": 12, "toronto": 12, "ontario": 12, "chennai": 12, "respective": 12, "marshals": 12, "virginia": 12, "carbine": 12, "designated": 12, "servant": 12, "magdalene": 12, "humpert": 12, "pieces": 12, "magistrate": 12, "brazilian": 12, "responding": 12, "purposes": 12, "rotating": 12, "recruited": 12, "removing": 12, "rubber": 12, "solely": 12, "guardia": 12}